{
  "created_at": "Mon May 01 18:28:52 +0000 2017",
  "id": 859112402306175000,
  "id_str": "859112402306174976",
  "full_text": "\"My favorite Meetup so far!\" #gdgfeedback https://t.co/bDcN8tYEfl",
  "truncated": false,
  "display_text_range": [0, 41],
  "entities": {
    "hashtags": [
      {
        "text": "gdgfeedback",
        "indices": [29, 41]
      }
    ],
    "symbols": [],
    "user_mentions": [],
    "urls": [],
    "media": [
      {
        "id": 859111722174607400,
        "id_str": "859111722174607361",
        "indices": [42, 65],
        "media_url": "http://pbs.twimg.com/media/C-wtjz6XcAEBnKU.jpg",
        "media_url_https": "https://pbs.twimg.com/media/C-wtjz6XcAEBnKU.jpg",
        "url": "https://t.co/bDcN8tYEfl",
        "display_url": "pic.twitter.com/bDcN8tYEfl",
        "expanded_url": "https://twitter.com/gdgmadison/status/859112402306174976/photo/1",
        "type": "photo",
        "sizes": {
          "thumb": {
            "w": 150,
            "h": 150,
            "resize": "crop"
          },
          "large": {
            "w": 2048,
            "h": 1536,
            "resize": "fit"
          },
          "small": {
            "w": 680,
            "h": 510,
            "resize": "fit"
          },
          "medium": {
            "w": 1200,
            "h": 900,
            "resize": "fit"
          }
        }
      }
    ]
  },
  "extended_entities": {
    "media": [
      {
        "id": 859111722174607400,
        "id_str": "859111722174607361",
        "indices": [42, 65],
        "media_url": "http://pbs.twimg.com/media/C-wtjz6XcAEBnKU.jpg",
        "media_url_https": "https://pbs.twimg.com/media/C-wtjz6XcAEBnKU.jpg",
        "url": "https://t.co/bDcN8tYEfl",
        "display_url": "pic.twitter.com/bDcN8tYEfl",
        "expanded_url": "https://twitter.com/gdgmadison/status/859112402306174976/photo/1",
        "type": "photo",
        "sizes": {
          "thumb": {
            "w": 150,
            "h": 150,
            "resize": "crop"
          },
          "large": {
            "w": 2048,
            "h": 1536,
            "resize": "fit"
          },
          "small": {
            "w": 680,
            "h": 510,
            "resize": "fit"
          },
          "medium": {
            "w": 1200,
            "h": 900,
            "resize": "fit"
          }
        }
      }
    ]
  },
  "source": "<a href=\"http://twitter.com\" rel=\"nofollow\">Twitter Web Client</a>",
  "in_reply_to_status_id": null,
  "in_reply_to_status_id_str": null,
  "in_reply_to_user_id": null,
  "in_reply_to_user_id_str": null,
  "in_reply_to_screen_name": null,
  "user": {
    "id": 60940193,
    "id_str": "60940193",
    "name": "GDG Madison",
    "screen_name": "gdgmadison",
    "location": "Madison, WI",
    "description": "Google Developer Group Madison. Hosting @DevFestWI Sept 28th.",
    "url": "https://t.co/jmpo3XZoV1",
    "entities": {
      "url": {
        "urls": [
          {
            "url": "https://t.co/jmpo3XZoV1",
            "expanded_url": "https://gdgmadison.com",
            "display_url": "gdgmadison.com",
            "indices": [0, 23]
          }
        ]
      },
      "description": {
        "urls": []
      }
    },
    "protected": false,
    "followers_count": 169,
    "friends_count": 50,
    "listed_count": 16,
    "created_at": "Tue Jul 28 15:57:37 +0000 2009",
    "favourites_count": 245,
    "utc_offset": null,
    "time_zone": null,
    "geo_enabled": true,
    "verified": false,
    "statuses_count": 590,
    "lang": null,
    "contributors_enabled": false,
    "is_translator": false,
    "is_translation_enabled": false,
    "profile_background_color": "000000",
    "profile_background_image_url": "http://abs.twimg.com/images/themes/theme9/bg.gif",
    "profile_background_image_url_https": "https://abs.twimg.com/images/themes/theme9/bg.gif",
    "profile_background_tile": false,
    "profile_image_url": "http://pbs.twimg.com/profile_images/1111957581914873856/WQ60P3yw_normal.jpg",
    "profile_image_url_https": "https://pbs.twimg.com/profile_images/1111957581914873856/WQ60P3yw_normal.jpg",
    "profile_banner_url": "https://pbs.twimg.com/profile_banners/60940193/1426795386",
    "profile_link_color": "2196F3",
    "profile_sidebar_border_color": "000000",
    "profile_sidebar_fill_color": "000000",
    "profile_text_color": "000000",
    "profile_use_background_image": false,
    "has_extended_profile": false,
    "default_profile": false,
    "default_profile_image": false,
    "following": true,
    "follow_request_sent": false,
    "notifications": false,
    "translator_type": "none"
  },
  "geo": null,
  "coordinates": null,
  "place": null,
  "contributors": null,
  "is_quote_status": false,
  "retweet_count": 3,
  "favorite_count": 5,
  "favorited": false,
  "retweeted": false,
  "possibly_sensitive": false,
  "possibly_sensitive_appealable": false,
  "lang": "en"
}
