[
  {
    "id": "webcomponents",
    "primaryColor": {
      "r": 33,
      "b": 150,
      "g": 243
    },
    "complementaryColor": {
      "r": 0,
      "b": 0,
      "g": 0
    }
  },
  {
    "id": "progressivewebapps",
    "primaryColor": {
      "r": 139,
      "b": 195,
      "g": 74
    },
    "complementaryColor": {
      "r": 255,
      "b": 255,
      "g": 255
    }
  },
  {
    "id": "polymer",
    "primaryColor": {
      "r": 245,
      "b": 0,
      "g": 87
    },
    "complementaryColor": {
      "r": 255,
      "b": 255,
      "g": 255
    }
  },
  {
    "id": "twitterapi",
    "primaryColor": {
      "r": 29,
      "b": 161,
      "g": 242
    },
    "complementaryColor": {
      "r": 0,
      "b": 0,
      "g": 0
    }
  },
  {
    "id": "php",
    "primaryColor": {
      "r": 136,
      "b": 146,
      "g": 190
    },
    "complementaryColor": {
      "r": 255,
      "b": 255,
      "g": 255
    }
  },
  {
    "id": "rails",
    "primaryColor": {
      "r": 204,
      "b": 0,
      "g": 0
    },
    "complementaryColor": {
      "r": 255,
      "b": 255,
      "g": 255
    }
  },
  {
    "id": "ruby",
    "primaryColor": {
      "r": 204,
      "b": 52,
      "g": 45
    },
    "complementaryColor": {
      "r": 255,
      "b": 255,
      "g": 255
    }
  },
  {
    "id": "firebase",
    "primaryColor": {
      "r": 255,
      "b": 152,
      "g": 0
    },
    "complementaryColor": {
      "r": 0,
      "b": 0,
      "g": 0
    }
  },
  {
    "id": "cli",
    "primaryColor": {
      "r": 33,
      "b": 33,
      "g": 33
    },
    "complementaryColor": {
      "r": 255,
      "b": 255,
      "g": 255
    }
  },
  {
    "id": "actionsongoogle",
    "primaryColor": {
      "r": 66,
      "b": 133,
      "g": 244
    },
    "complementaryColor": {
      "r": 0,
      "b": 0,
      "g": 0
    }
  },
  {
    "id": "angular",
    "primaryColor": {
      "r": 218,
      "b": 11,
      "g": 55
    },
    "complementaryColor": {
      "r": 255,
      "b": 255,
      "g": 255
    }
  },
  {
    "id": "googleio",
    "primaryColor": {
      "r": 63,
      "b": 231,
      "g": 184
    },
    "complementaryColor": {
      "r": 0,
      "b": 0,
      "g": 0
    }
  },
  {
    "id": "video",
    "primaryColor": {
      "r": 156,
      "b": 39,
      "g": 176
    },
    "complementaryColor": {
      "r": 255,
      "b": 255,
      "g": 255
    }
  },
  {
    "id": "⚡",
    "primaryColor": {
      "r": 33,
      "b": 33,
      "g": 33
    },
    "complementaryColor": {
      "r": 255,
      "b": 255,
      "g": 255
    }
  },
  {
    "id": "threejs",
    "primaryColor": {
      "r": 236,
      "b": 239,
      "g": 241
    },
    "complementaryColor": {
      "r": 0,
      "b": 0,
      "g": 0
    }
  },
  {
    "id": "reviews",
    "primaryColor": {
      "r": 96,
      "b": 125,
      "g": 139
    },
    "complementaryColor": {
      "r": 255,
      "b": 255,
      "g": 255
    }
  },
  {
    "id": "materialdesign",
    "primaryColor": {
      "r": 144,
      "b": 144,
      "g": 144
    },
    "complementaryColor": {
      "r": 255,
      "b": 255,
      "g": 255
    }
  },
  {
    "id": "demo",
    "primaryColor": {
      "r": 33,
      "b": 33,
      "g": 33
    },
    "complementaryColor": {
      "r": 255,
      "b": 255,
      "g": 255
    }
  },
  {
    "id": "culture",
    "primaryColor": {
      "r": 255,
      "b": 235,
      "g": 59
    },
    "complementaryColor": {
      "r": 0,
      "b": 0,
      "g": 0
    }
  },
  {
    "id": "javascript",
    "primaryColor": {
      "r": 247,
      "b": 224,
      "g": 24
    },
    "complementaryColor": {
      "r": 0,
      "b": 0,
      "g": 0
    }
  },
  {
    "id": "nutmeg",
    "primaryColor": {
      "r": 77,
      "b": 89,
      "g": 123
    },
    "complementaryColor": {
      "r": 255,
      "b": 255,
      "g": 255
    }
  },
  {
    "id": "perfmatters",
    "primaryColor": {
      "r": 248,
      "b": 172,
      "g": 4
    },
    "complementaryColor": {
      "r": 0,
      "b": 0,
      "g": 0
    }
  },
  {
    "id": "workshop",
    "primaryColor": {
      "r": 0,
      "b": 150,
      "g": 136
    },
    "complementaryColor": {
      "r": 255,
      "b": 255,
      "g": 255
    }
  },
  {
    "id": "typescript",
    "primaryColor": {
      "r": 0,
      "b": 122,
      "g": 204
    },
    "complementaryColor": {
      "r": 0,
      "b": 0,
      "g": 0
    }
  },
  {
    "id": "flutter",
    "primaryColor": {
      "r": 0,
      "b": 145,
      "g": 234
    },
    "complementaryColor": {
      "r": 0,
      "b": 0,
      "g": 0
    }
  }
]
